{
    "mal_id": 171195,
    "magazine_slug": "wsj",
    "hikka_slug": "exorcist-no-kiyoshi-kun-414a35",
    "poster": "https://cdn.hikka.io/content/manga/exorcist-no-kiyoshi-kun-414a35/A-ZUnOmHvpgA3i7PEtWlHw.jpg",
    "banner": "https://media.kitsu.app/manga/72236/cover_image/8ce7c5de8d559e4b6aa13dce4f5ebf37.jpg",
    "title": "Ultimate Exorcist Kiyoshi",
    "title_ua": "",
    "score": 7.15,
    "volumes_count": null,
    "chapters_count": null,
    "chapters_breaks": [],
    "chapters": [],
    "specials": [],
    "status": "ongoing"
}
